Metadata-Version: 2.1
Name: torch-clip
Version: 0.0.6
Summary: torch-clip a library to improve optimization methods by clipping off heavy-tailed gradient. This makes it possible to increase the accuracy and speed of convergence during the training of neural networks on a specific number of tasks.
Home-page: 
Author: Nikolay
Author-email: kutuzov.nv@phystech.edu
License: MIT
Keywords: python,torch,clipping
